{
  "version": "4.0",
  "created_at": "2026-04-07T23:38:59.569096",
  "last_trained": null,
  "user_facts": [
    {
      "fact": "User loves Python",
      "confidence": 0.9,
      "source": "test",
      "learned_at": "2026-04-07T23:38:59.569106"
    }
  ],
  "preferences": {},
  "topics": {
    "AI": {
      "count": 5,
      "last_seen": "2026-04-08T15:49:28.958212"
    }
  },
  "communication_style": {},
  "projects": [
    {
      "name": "Lirox Mind Agent",
      "description": "A cool AI project",
      "first_seen": "2026-04-07T23:38:59.569256",
      "last_seen": "2026-04-08T15:49:28.958075"
    }
  ],
  "dislikes": [],
  "interaction_patterns": {},
  "custom_notes": [],
  "sessions_trained": 0,
  "total_interactions": 0
}